CHANGELOG.txt
LICENSE.txt
MANIFEST.in
README.rst
setup.cfg
setup.py
loan_payoff_tools/__init__.py
loan_payoff_tools/analysis.py
loan_payoff_tools/max_payment_determiner.py
loan_payoff_tools/money.py
loan_payoff_tools/payment_manager.py
loan_payoff_tools/payoff_calculator.py
loan_payoff_tools/utils.py
loan_payoff_tools.egg-info/PKG-INFO
loan_payoff_tools.egg-info/SOURCES.txt
loan_payoff_tools.egg-info/dependency_links.txt
loan_payoff_tools.egg-info/requires.txt
loan_payoff_tools.egg-info/top_level.txt