Metadata-Version: 1.1
Name: loan-payoff-tools
Version: 0.1.0
Summary: Simulates multiple different scenarios in which to payoff loans.
Home-page: https://github.com/phillipgreenii/optimize_loan_payoff
Author: Phillip Green II
Author-email: phillip.green.ii@gmail.com
License: MIT
Download-URL: https://github.com/phillipgreenii/optimize_loan_payoff/tarball/0.1.0
Keywords: loans payoff simulate debt college
Platform: UNKNOWN
Classifier: Development Status :: 3 - Alpha
Classifier: Intended Audience :: Developers
Classifier: Topic :: Office/Business :: Financial
Classifier: Topic :: Other/Nonlisted Topic
Classifier: Operating System :: MacOS :: MacOS X
Classifier: Operating System :: Microsoft :: Windows
Classifier: Operating System :: POSIX
Classifier: License :: OSI Approved :: MIT License
Classifier: Programming Language :: Python
Classifier: Programming Language :: Python :: 2
Classifier: Programming Language :: Python :: 2.7
